pyros_common/__init__.py
pyros_common/exceptions.py
pyros_common-0.5.4.dist-info/METADATA
pyros_common-0.5.4.dist-info/RECORD
pyros_common-0.5.4.dist-info/WHEEL
pyros_common-0.5.4.dist-info/top_level.txt
pyros_interfaces_common/__init__.py
pyros_interfaces_common/_version.py
pyros_interfaces_common/basemsg.py
pyros_interfaces_common/basenode.py
pyros_interfaces_common/pyros_prtcl.py
pyros_interfaces_common/regex_tools.py
pyros_interfaces_common/transient.py
pyros_interfaces_common/transient_if.py
pyros_interfaces_common/transient_if_pool.py
pyros_interfaces_common/utils.py
pyros_interfaces_mock/__init__.py
pyros_interfaces_mock/exceptions.py
pyros_interfaces_mock/mockinterface.py
pyros_interfaces_mock/mockmessage.py
pyros_interfaces_mock/mockparam.py
pyros_interfaces_mock/mockparampool.py
pyros_interfaces_mock/mockpublisher.py
pyros_interfaces_mock/mockpublisherpool.py
pyros_interfaces_mock/mockservice.py
pyros_interfaces_mock/mockservicepool.py
pyros_interfaces_mock/mocksubscriber.py
pyros_interfaces_mock/mocksubscriberpool.py
pyros_interfaces_mock/mocksystem.py
pyros_interfaces_mock/pyros_mock.py
