Metadata-Version: 1.0
Name: pyros-common
Version: 0.5.4
Summary: Common interface packages for Pyros framework
Home-page: http://github.com/asmodehn/pyros-common
Author: AlexV
Author-email: asmodehn@gmail.com
License: BSD
Platform: UNKNOWN
